LICENSE.txt
MANIFEST.in
setup.cfg
setup.py
./speleopy/__init__.py
./speleopy/damp.py
./speleopy/record_class.py
./speleopy/sealevel.py
./speleopy/version.py
SpeleoPy.egg-info/PKG-INFO
SpeleoPy.egg-info/SOURCES.txt
SpeleoPy.egg-info/dependency_links.txt
SpeleoPy.egg-info/not-zip-safe
SpeleoPy.egg-info/top_level.txt
speleopy/__init__.py
speleopy/damp.py
speleopy/record_class.py
speleopy/sealevel.py
speleopy/version.py
speleopy/data/sealevel.txt