Metadata-Version: 1.1
Name: SpeleoPy
Version: 0.1.4
Summary: Paleoclimate data and age modelling
Home-page: https://github.com/mscross/SpeleoPy
Author: Mellissa Cross
Author-email: mellissa.cross@gmail.com
License: Modified BSD
Download-URL: https://pypi.python.org/pypi/SpeleoPy
Platform: UNKNOWN
Classifier: Development Status :: 4 - Beta
Classifier: Environment :: Console
Classifier: Intended Audience :: Developers
Classifier: Intended Audience :: Science/Research
Classifier: License :: OSI Approved :: BSD License
Classifier: Programming Language :: Python
Classifier: Programming Language :: Python :: 3
Classifier: Topic :: Scientific/Engineering
Classifier: Operating System :: Microsoft :: Windows
Classifier: Operating System :: POSIX
Classifier: Operating System :: Unix
Classifier: Operating System :: MacOS
